localstack_extension_ecs_container_endpoints/__init__.py
localstack_extension_ecs_container_endpoints/extension.py
localstack_extension_ecs_container_endpoints-0.1.3.dist-info/LICENSE.txt
localstack_extension_ecs_container_endpoints-0.1.3.dist-info/METADATA
localstack_extension_ecs_container_endpoints-0.1.3.dist-info/WHEEL
localstack_extension_ecs_container_endpoints-0.1.3.dist-info/entry_points.txt
localstack_extension_ecs_container_endpoints-0.1.3.dist-info/top_level.txt
localstack_extension_ecs_container_endpoints-0.1.3.dist-info/RECORD
