Metadata-Version: 2.2
Name: localstack-extension-ecs-container-endpoints
Version: 0.1.3
Summary: LocalStack Extension: localstack-extension-ecs-container-endpoints
Author-email: "Mark S." <the@wondersmith.io>
License: AGPL-3.0-or-later
Project-URL: Homepage, https://github.com/the-wondersmith/localstack-extension-ecs-container-endpoints
Keywords: localstack,localstack-extension,extension
Requires-Python: >=3.11
License-File: LICENSE.txt
